{
  "lastUpdated": "2026-04-06T14:23:40.657Z",
  "source": "DRatings",
  "url": "https://www.dratings.com/predictor/nhl-hockey-predictions/",
  "count": 4,
  "predictions": [
    {
      "awayTeam": "TBL",
      "homeTeam": "BUF",
      "awayProb": 0.5329999999999999,
      "homeProb": 0.467,
      "source": "DRatings",
      "scrapedAt": 1775485429195
    },
    {
      "awayTeam": "SEA",
      "homeTeam": "WPG",
      "awayProb": 0.41,
      "homeProb": 0.59,
      "source": "DRatings",
      "scrapedAt": 1775485429195
    },
    {
      "awayTeam": "CHI",
      "homeTeam": "SJS",
      "awayProb": 0.44,
      "homeProb": 0.56,
      "source": "DRatings",
      "scrapedAt": 1775485429195
    },
    {
      "awayTeam": "NSH",
      "homeTeam": "LAK",
      "awayProb": 0.446,
      "homeProb": 0.5539999999999999,
      "source": "DRatings",
      "scrapedAt": 1775485429195
    }
  ]
}