{
  "NHL": {
    "bos_buf": {
      "away": "Bruins",
      "home": "Sabres",
      "positions": [
        {
          "wallet": "0x84cfffc3f16dcc353094de30d4a45226eccd2f63",
          "name": "mooseborzoi",
          "tier": "ELITE",
          "totalPnl": 341627,
          "sportPnlTotal": 341627,
          "outcome": "Sabres",
          "side": "home",
          "marketType": "ml",
          "size": 12,
          "avgPrice": 0.61,
          "invested": 7,
          "curPrice": 0.605,
          "currentValue": 7,
          "pnl": 0,
          "firstSeen": "2026-04-26T21:54:29.296Z",
          "sportPnl": 341627,
          "sportVerified": true,
          "sportROI": 6.5,
          "avgSportBet": 6945,
          "leaderboardRank": 196,
          "sportsLbPercentileTop": 87,
          "sportVol": 5244292.9169510035,
          "monthlyPnl": 341627.2713669236,
          "monthlyQualified": true
        },
        {
          "wallet": "0xee00ba338c59557141789b127927a55f5cc5cea1",
          "name": "S-Works",
          "tier": "ELITE",
          "totalPnl": 2454724,
          "sportPnlTotal": 2454724,
          "outcome": "Sabres",
          "side": "home",
          "marketType": "ml",
          "size": 7,
          "avgPrice": 0.9,
          "invested": 6,
          "curPrice": 0.915,
          "currentValue": 6,
          "pnl": 0,
          "firstSeen": "2026-04-27T11:48:32.618Z",
          "sportPnl": 2454724,
          "sportVerified": true,
          "sportROI": 1.4,
          "avgSportBet": 28025,
          "leaderboardRank": 21,
          "sportsLbPercentileTop": 98.67,
          "sportVol": 176518250.49031,
          "monthlyPnl": 571836.4215031425,
          "monthlyQualified": true
        }
      ],
      "summary": {
        "sharpAway": 0,
        "sharpHome": 2,
        "awayInvested": 0,
        "homeInvested": 13,
        "consensus": "home",
        "totalInvested": 13
      }
    },
    "min_dal": {
      "away": "Wild",
      "home": "Stars",
      "positions": [
        {
          "wallet": "0x03e8a544e97eeff5753bc1e90d46e5ef22af1697",
          "name": "weflyhigh",
          "tier": "ELITE",
          "totalPnl": 1508274,
          "sportPnlTotal": 1508274,
          "outcome": "Stars",
          "side": "home",
          "marketType": "ml",
          "size": 12353,
          "avgPrice": 0.54,
          "invested": 6671,
          "curPrice": 0.545,
          "currentValue": 6732,
          "pnl": 62,
          "firstSeen": "2026-04-28T07:06:31.613Z",
          "sportPnl": 1508274,
          "sportVerified": true,
          "sportROI": 1.3,
          "avgSportBet": 74754,
          "leaderboardRank": 36,
          "sportsLbPercentileTop": 97.67,
          "sportVol": 116915113.61725001,
          "monthlyPnl": 307268.3385908813,
          "monthlyQualified": true
        },
        {
          "wallet": "0xfb681e23db8d1cca8a6b7e2a70a29e000ddfa240",
          "name": "stakesroyale",
          "tier": "ELITE",
          "totalPnl": 153151,
          "sportPnlTotal": 153151,
          "outcome": "Wild",
          "side": "away",
          "marketType": "ml",
          "size": 8000,
          "avgPrice": 0.45,
          "invested": 3600,
          "curPrice": 0.455,
          "currentValue": 3640,
          "pnl": 40,
          "firstSeen": "2026-04-28T06:45:25.559Z",
          "sportPnl": 153151,
          "sportVerified": true,
          "sportROI": 3.6,
          "avgSportBet": 3259,
          "leaderboardRank": 395,
          "sportsLbPercentileTop": 73.73,
          "sportVol": 4251321.501175,
          "monthlyPnl": 74535.59924591496,
          "monthlyQualified": true
        },
        {
          "wallet": "0x84cfffc3f16dcc353094de30d4a45226eccd2f63",
          "name": "mooseborzoi",
          "tier": "ELITE",
          "totalPnl": 341627,
          "sportPnlTotal": 341627,
          "outcome": "Stars",
          "side": "home",
          "marketType": "ml",
          "size": 1772,
          "avgPrice": 0.552,
          "invested": 979,
          "curPrice": 0.545,
          "currentValue": 966,
          "pnl": -13,
          "firstSeen": "2026-04-26T03:25:21.163Z",
          "sportPnl": 341627,
          "sportVerified": true,
          "sportROI": 6.5,
          "avgSportBet": 6945,
          "leaderboardRank": 196,
          "sportsLbPercentileTop": 87,
          "sportVol": 5244292.9169510035,
          "monthlyPnl": 341627.2713669236,
          "monthlyQualified": true
        },
        {
          "wallet": "0x32ccd9015a900fde62040162a04bedf093c668b3",
          "name": "pilotlady",
          "tier": "ELITE",
          "totalPnl": 133140,
          "sportPnlTotal": 133140,
          "outcome": "Stars",
          "side": "home",
          "marketType": "ml",
          "size": 16,
          "avgPrice": 0.55,
          "invested": 9,
          "curPrice": 0.545,
          "currentValue": 9,
          "pnl": 0,
          "firstSeen": "2026-04-28T01:40:13.979Z",
          "sportPnl": 133140,
          "sportVerified": true,
          "sportROI": 1,
          "avgSportBet": 1565,
          "leaderboardRank": 434,
          "sportsLbPercentileTop": 71.13,
          "sportVol": 13220632.717709998,
          "monthlyPnl": 133140.4524151096,
          "monthlyQualified": true
        }
      ],
      "summary": {
        "sharpAway": 1,
        "sharpHome": 3,
        "awayInvested": 3600,
        "homeInvested": 7659,
        "consensus": "home",
        "totalInvested": 11259
      }
    },
    "ana_edm": {
      "away": "Ducks",
      "home": "Oilers",
      "positions": [
        {
          "wallet": "0x13414a77a4be48988851c73dfd824d0168e70853",
          "name": "NRASCHATTER",
          "tier": "ELITE",
          "totalPnl": 630815,
          "sportPnlTotal": 630815,
          "outcome": "Oilers",
          "side": "home",
          "marketType": "ml",
          "size": 100407,
          "avgPrice": 0.423,
          "invested": 42513,
          "curPrice": 0.215,
          "currentValue": 21588,
          "pnl": -20930,
          "firstSeen": "2026-04-27T06:33:26.417Z",
          "sportPnl": 630815,
          "sportVerified": true,
          "sportROI": 1.4,
          "avgSportBet": 6471,
          "leaderboardRank": 121,
          "sportsLbPercentileTop": 92,
          "sportVol": 46374306.752488986
        },
        {
          "wallet": "0x84cfffc3f16dcc353094de30d4a45226eccd2f63",
          "name": "mooseborzoi",
          "tier": "ELITE",
          "totalPnl": 341627,
          "sportPnlTotal": 341627,
          "outcome": "Oilers",
          "side": "home",
          "marketType": "ml",
          "size": 6641,
          "avgPrice": 0.593,
          "invested": 3940,
          "curPrice": 0.605,
          "currentValue": 4018,
          "pnl": 78,
          "firstSeen": "2026-04-27T06:34:36.127Z",
          "sportPnl": 341627,
          "sportVerified": true,
          "sportROI": 6.5,
          "avgSportBet": 6945,
          "leaderboardRank": 196,
          "sportsLbPercentileTop": 87,
          "sportVol": 5244292.9169510035,
          "monthlyPnl": 341627.2713669236,
          "monthlyQualified": true
        },
        {
          "wallet": "0xfb681e23db8d1cca8a6b7e2a70a29e000ddfa240",
          "name": "stakesroyale",
          "tier": "ELITE",
          "totalPnl": 153151,
          "sportPnlTotal": 153151,
          "outcome": "Ducks",
          "side": "away",
          "marketType": "ml",
          "size": 12393,
          "avgPrice": 0.296,
          "invested": 3667,
          "curPrice": 0.785,
          "currentValue": 9729,
          "pnl": 6060,
          "firstSeen": "2026-04-27T06:36:57.496Z",
          "sportPnl": 153151,
          "sportVerified": true,
          "sportROI": 3.6,
          "avgSportBet": 3259,
          "leaderboardRank": 395,
          "sportsLbPercentileTop": 73.73,
          "sportVol": 4251321.501175,
          "monthlyPnl": 74535.59924591496,
          "monthlyQualified": true
        },
        {
          "wallet": "0x5b6331e7ff0831a3fe2ed12004747db1a9c911a4",
          "name": "neutralwave23",
          "tier": "ELITE",
          "totalPnl": 306332,
          "sportPnlTotal": 306332,
          "outcome": "Oilers",
          "side": "home",
          "marketType": "ml",
          "size": 2800,
          "avgPrice": 0.61,
          "invested": 1708,
          "curPrice": 0.605,
          "currentValue": 1694,
          "pnl": -14,
          "firstSeen": "2026-04-27T19:45:10.859Z",
          "sportPnl": 306332,
          "sportVerified": true,
          "sportROI": 44.2,
          "avgSportBet": 1543,
          "leaderboardRank": null,
          "sportsLbPercentileTop": null,
          "sportVol": 692672
        }
      ],
      "summary": {
        "sharpAway": 1,
        "sharpHome": 3,
        "awayInvested": 3667,
        "homeInvested": 48161,
        "consensus": "home",
        "totalInvested": 51828
      }
    },
    "mtl_tbl": {
      "away": "NHL Playoffs: Who Will Win Series? - Canadiens",
      "home": "Lightning",
      "positions": [
        {
          "wallet": "0x13414a77a4be48988851c73dfd824d0168e70853",
          "name": "NRASCHATTER",
          "tier": "ELITE",
          "totalPnl": 630815,
          "sportPnlTotal": 630815,
          "outcome": "Habs",
          "side": "away",
          "marketType": "ml",
          "size": 13283,
          "avgPrice": 0.59,
          "invested": 7837,
          "curPrice": 0.375,
          "currentValue": 4981,
          "pnl": -2856,
          "firstSeen": "2026-04-27T03:28:57.043Z",
          "sportPnl": 630815,
          "sportVerified": true,
          "sportROI": 1.4,
          "avgSportBet": 6471,
          "leaderboardRank": 121,
          "sportsLbPercentileTop": 92,
          "sportVol": 46374306.752488986
        }
      ],
      "summary": {
        "sharpAway": 1,
        "sharpHome": 0,
        "awayInvested": 7837,
        "homeInvested": 0,
        "consensus": "away",
        "totalInvested": 7837
      }
    }
  },
  "CBB": {},
  "MLB": {
    "tbr_cle": {
      "away": "Tampa Bay Rays",
      "home": "Cleveland Guardians",
      "positions": [
        {
          "wallet": "0x84cfffc3f16dcc353094de30d4a45226eccd2f63",
          "name": "mooseborzoi",
          "tier": "ELITE",
          "totalPnl": 341627,
          "sportPnlTotal": 341627,
          "outcome": "Tampa Bay Rays",
          "side": "away",
          "marketType": "ml",
          "size": 2452,
          "avgPrice": 0.44,
          "invested": 1079,
          "curPrice": 0.445,
          "currentValue": 1091,
          "pnl": 12,
          "firstSeen": "2026-04-28T00:59:26.990Z",
          "sportPnl": 341627,
          "sportVerified": true,
          "sportROI": 6.5,
          "avgSportBet": 6945,
          "leaderboardRank": 196,
          "sportsLbPercentileTop": 87,
          "sportVol": 5244292.9169510035,
          "monthlyPnl": 341627.2713669236,
          "monthlyQualified": true
        },
        {
          "wallet": "0x32ccd9015a900fde62040162a04bedf093c668b3",
          "name": "pilotlady",
          "tier": "ELITE",
          "totalPnl": 133140,
          "sportPnlTotal": 133140,
          "outcome": "Tampa Bay Rays",
          "side": "away",
          "marketType": "ml",
          "size": 41,
          "avgPrice": 0.44,
          "invested": 18,
          "curPrice": 0.445,
          "currentValue": 18,
          "pnl": 0,
          "firstSeen": "2026-04-28T06:45:53.907Z",
          "sportPnl": 133140,
          "sportVerified": true,
          "sportROI": 1,
          "avgSportBet": 1565,
          "leaderboardRank": 434,
          "sportsLbPercentileTop": 71.13,
          "sportVol": 13220632.717709998,
          "monthlyPnl": 133140.4524151096,
          "monthlyQualified": true
        }
      ],
      "summary": {
        "sharpAway": 2,
        "sharpHome": 0,
        "awayInvested": 1097,
        "homeInvested": 0,
        "consensus": "away",
        "totalInvested": 1097
      }
    },
    "hou_bal": {
      "away": "Houston Astros",
      "home": "Baltimore Orioles",
      "positions": [
        {
          "wallet": "0x1117eade222413335b7ec959e5b48c1d3dbc3532",
          "name": "benwyatt",
          "tier": "ELITE",
          "totalPnl": 219420,
          "sportPnlTotal": 219420,
          "outcome": "Baltimore Orioles",
          "side": "home",
          "marketType": "ml",
          "size": 1819,
          "avgPrice": 0.55,
          "invested": 1001,
          "curPrice": 0.555,
          "currentValue": 1010,
          "pnl": 9,
          "firstSeen": "2026-04-28T06:44:19.643Z",
          "sportPnl": 219420,
          "sportVerified": true,
          "sportROI": 3.1,
          "avgSportBet": 9859,
          "leaderboardRank": 102,
          "sportsLbPercentileTop": 89.9,
          "sportVol": 7027404.434521999,
          "monthlyPnl": 219420.06354367128,
          "monthlyQualified": true
        },
        {
          "wallet": "0x84cfffc3f16dcc353094de30d4a45226eccd2f63",
          "name": "mooseborzoi",
          "tier": "ELITE",
          "totalPnl": 341627,
          "sportPnlTotal": 341627,
          "outcome": "Houston Astros",
          "side": "away",
          "marketType": "ml",
          "size": 1730,
          "avgPrice": 0.45,
          "invested": 778,
          "curPrice": 0.445,
          "currentValue": 770,
          "pnl": -9,
          "firstSeen": "2026-04-27T23:46:10.361Z",
          "sportPnl": 341627,
          "sportVerified": true,
          "sportROI": 6.5,
          "avgSportBet": 6945,
          "leaderboardRank": 196,
          "sportsLbPercentileTop": 87,
          "sportVol": 5244292.9169510035,
          "monthlyPnl": 341627.2713669236,
          "monthlyQualified": true
        }
      ],
      "summary": {
        "sharpAway": 1,
        "sharpHome": 1,
        "awayInvested": 778,
        "homeInvested": 1001,
        "consensus": "home",
        "totalInvested": 1779
      }
    },
    "det_atl": {
      "away": "Detroit Tigers",
      "home": "Atlanta Braves",
      "positions": [
        {
          "wallet": "0x84cfffc3f16dcc353094de30d4a45226eccd2f63",
          "name": "mooseborzoi",
          "tier": "ELITE",
          "totalPnl": 341627,
          "sportPnlTotal": 341627,
          "outcome": "Atlanta Braves",
          "side": "home",
          "marketType": "ml",
          "size": 804,
          "avgPrice": 0.61,
          "invested": 491,
          "curPrice": 0.525,
          "currentValue": 422,
          "pnl": -68,
          "firstSeen": "2026-04-27T18:09:50.070Z",
          "sportPnl": 341627,
          "sportVerified": true,
          "sportROI": 6.5,
          "avgSportBet": 6945,
          "leaderboardRank": 196,
          "sportsLbPercentileTop": 87,
          "sportVol": 5244292.9169510035,
          "monthlyPnl": 341627.2713669236,
          "monthlyQualified": true
        }
      ],
      "summary": {
        "sharpAway": 0,
        "sharpHome": 1,
        "awayInvested": 0,
        "homeInvested": 491,
        "consensus": "home",
        "totalInvested": 491
      }
    },
    "stl_pit": {
      "away": "St. Louis Cardinals",
      "home": "Pittsburgh Pirates",
      "positions": [
        {
          "wallet": "0x84cfffc3f16dcc353094de30d4a45226eccd2f63",
          "name": "mooseborzoi",
          "tier": "ELITE",
          "totalPnl": 341627,
          "sportPnlTotal": 341627,
          "outcome": "Pittsburgh Pirates",
          "side": "home",
          "marketType": "ml",
          "size": 579,
          "avgPrice": 0.59,
          "invested": 342,
          "curPrice": 0.585,
          "currentValue": 339,
          "pnl": -3,
          "firstSeen": "2026-04-28T06:43:15.810Z",
          "sportPnl": 341627,
          "sportVerified": true,
          "sportROI": 6.5,
          "avgSportBet": 6945,
          "leaderboardRank": 196,
          "sportsLbPercentileTop": 87,
          "sportVol": 5244292.9169510035,
          "monthlyPnl": 341627.2713669236,
          "monthlyQualified": true
        }
      ],
      "summary": {
        "sharpAway": 0,
        "sharpHome": 1,
        "awayInvested": 0,
        "homeInvested": 342,
        "consensus": "home",
        "totalInvested": 342
      }
    },
    "wsh_nym": {
      "away": "Washington Nationals",
      "home": "New York Mets",
      "positions": [
        {
          "wallet": "0x84cfffc3f16dcc353094de30d4a45226eccd2f63",
          "name": "mooseborzoi",
          "tier": "ELITE",
          "totalPnl": 341627,
          "sportPnlTotal": 341627,
          "outcome": "New York Mets",
          "side": "home",
          "marketType": "ml",
          "size": 446,
          "avgPrice": 0.62,
          "invested": 276,
          "curPrice": 0.615,
          "currentValue": 274,
          "pnl": -2,
          "firstSeen": "2026-04-28T04:04:44.721Z",
          "sportPnl": 341627,
          "sportVerified": true,
          "sportROI": 6.5,
          "avgSportBet": 6945,
          "leaderboardRank": 196,
          "sportsLbPercentileTop": 87,
          "sportVol": 5244292.9169510035,
          "monthlyPnl": 341627.2713669236,
          "monthlyQualified": true
        }
      ],
      "summary": {
        "sharpAway": 0,
        "sharpHome": 1,
        "awayInvested": 0,
        "homeInvested": 276,
        "consensus": "home",
        "totalInvested": 276
      }
    },
    "kcr_oak": {
      "away": "Kansas City Royals",
      "home": "Athletics",
      "positions": [
        {
          "wallet": "0x84cfffc3f16dcc353094de30d4a45226eccd2f63",
          "name": "mooseborzoi",
          "tier": "ELITE",
          "totalPnl": 341627,
          "sportPnlTotal": 341627,
          "outcome": "Athletics",
          "side": "home",
          "marketType": "ml",
          "size": 261,
          "avgPrice": 0.491,
          "invested": 128,
          "curPrice": 0.485,
          "currentValue": 127,
          "pnl": -1,
          "firstSeen": "2026-04-28T00:59:26.993Z",
          "sportPnl": 341627,
          "sportVerified": true,
          "sportROI": 6.5,
          "avgSportBet": 6945,
          "leaderboardRank": 196,
          "sportsLbPercentileTop": 87,
          "sportVol": 5244292.9169510035,
          "monthlyPnl": 341627.2713669236,
          "monthlyQualified": true
        }
      ],
      "summary": {
        "sharpAway": 0,
        "sharpHome": 1,
        "awayInvested": 0,
        "homeInvested": 128,
        "consensus": "home",
        "totalInvested": 128
      }
    },
    "nyy_tex": {
      "away": "New York Yankees",
      "home": "Texas Rangers",
      "positions": [
        {
          "wallet": "0x84cfffc3f16dcc353094de30d4a45226eccd2f63",
          "name": "mooseborzoi",
          "tier": "ELITE",
          "totalPnl": 341627,
          "sportPnlTotal": 341627,
          "outcome": "Texas Rangers",
          "side": "home",
          "marketType": "ml",
          "size": 113,
          "avgPrice": 0.45,
          "invested": 51,
          "curPrice": 0.465,
          "currentValue": 53,
          "pnl": 2,
          "firstSeen": "2026-04-27T06:34:36.128Z",
          "sportPnl": 341627,
          "sportVerified": true,
          "sportROI": 6.5,
          "avgSportBet": 6945,
          "leaderboardRank": 196,
          "sportsLbPercentileTop": 87,
          "sportVol": 5244292.9169510035,
          "monthlyPnl": 341627.2713669236,
          "monthlyQualified": true
        },
        {
          "wallet": "0x84cfffc3f16dcc353094de30d4a45226eccd2f63",
          "name": "mooseborzoi",
          "tier": "ELITE",
          "totalPnl": 341627,
          "sportPnlTotal": 341627,
          "outcome": "New York Yankees",
          "side": "away",
          "marketType": "ml",
          "size": 10,
          "avgPrice": 0.565,
          "invested": 6,
          "curPrice": 0.535,
          "currentValue": 5,
          "pnl": 0,
          "firstSeen": "2026-04-26T22:56:19.510Z",
          "sportPnl": 341627,
          "sportVerified": true,
          "sportROI": 6.5,
          "avgSportBet": 6945,
          "leaderboardRank": 196,
          "sportsLbPercentileTop": 87,
          "sportVol": 5244292.9169510035,
          "monthlyPnl": 341627.2713669236,
          "monthlyQualified": true
        }
      ],
      "summary": {
        "sharpAway": 1,
        "sharpHome": 1,
        "awayInvested": 6,
        "homeInvested": 51,
        "consensus": "home",
        "totalInvested": 57
      }
    },
    "bos_tor": {
      "away": "Boston Red Sox",
      "home": "Toronto Blue Jays",
      "positions": [
        {
          "wallet": "0x84cfffc3f16dcc353094de30d4a45226eccd2f63",
          "name": "mooseborzoi",
          "tier": "ELITE",
          "totalPnl": 341627,
          "sportPnlTotal": 341627,
          "outcome": "Boston Red Sox",
          "side": "away",
          "marketType": "ml",
          "size": 103,
          "avgPrice": 0.48,
          "invested": 49,
          "curPrice": 0.475,
          "currentValue": 49,
          "pnl": -1,
          "firstSeen": "2026-04-28T09:28:54.853Z",
          "sportPnl": 341627,
          "sportVerified": true,
          "sportROI": 6.5,
          "avgSportBet": 6945,
          "leaderboardRank": 196,
          "sportsLbPercentileTop": 87,
          "sportVol": 5244292.9169510035,
          "monthlyPnl": 341627.2713669236,
          "monthlyQualified": true
        }
      ],
      "summary": {
        "sharpAway": 1,
        "sharpHome": 0,
        "awayInvested": 49,
        "homeInvested": 0,
        "consensus": "away",
        "totalInvested": 49
      }
    },
    "sea_min": {
      "away": "Seattle Mariners",
      "home": "Minnesota Twins",
      "positions": [
        {
          "wallet": "0x84cfffc3f16dcc353094de30d4a45226eccd2f63",
          "name": "mooseborzoi",
          "tier": "ELITE",
          "totalPnl": 341627,
          "sportPnlTotal": 341627,
          "outcome": "Minnesota Twins",
          "side": "home",
          "marketType": "ml",
          "size": 60,
          "avgPrice": 0.48,
          "invested": 29,
          "curPrice": 0.46,
          "currentValue": 27,
          "pnl": -1,
          "firstSeen": "2026-04-27T22:45:53.364Z",
          "sportPnl": 341627,
          "sportVerified": true,
          "sportROI": 6.5,
          "avgSportBet": 6945,
          "leaderboardRank": 196,
          "sportsLbPercentileTop": 87,
          "sportVol": 5244292.9169510035,
          "monthlyPnl": 341627.2713669236,
          "monthlyQualified": true
        }
      ],
      "summary": {
        "sharpAway": 0,
        "sharpHome": 1,
        "awayInvested": 0,
        "homeInvested": 29,
        "consensus": "home",
        "totalInvested": 29
      }
    },
    "sfg_phi": {
      "away": "San Francisco Giants",
      "home": "Philadelphia Phillies",
      "positions": [
        {
          "wallet": "0x84cfffc3f16dcc353094de30d4a45226eccd2f63",
          "name": "mooseborzoi",
          "tier": "ELITE",
          "totalPnl": 341627,
          "sportPnlTotal": 341627,
          "outcome": "San Francisco Giants",
          "side": "away",
          "marketType": "ml",
          "size": 42,
          "avgPrice": 0.4,
          "invested": 17,
          "curPrice": 0.395,
          "currentValue": 16,
          "pnl": 0,
          "firstSeen": "2026-04-27T23:46:10.360Z",
          "sportPnl": 341627,
          "sportVerified": true,
          "sportROI": 6.5,
          "avgSportBet": 6945,
          "leaderboardRank": 196,
          "sportsLbPercentileTop": 87,
          "sportVol": 5244292.9169510035,
          "monthlyPnl": 341627.2713669236,
          "monthlyQualified": true
        }
      ],
      "summary": {
        "sharpAway": 1,
        "sharpHome": 0,
        "awayInvested": 17,
        "homeInvested": 0,
        "consensus": "away",
        "totalInvested": 17
      }
    },
    "mia_lad": {
      "away": "Miami Marlins",
      "home": "Los Angeles Dodgers",
      "positions": [
        {
          "wallet": "0x84cfffc3f16dcc353094de30d4a45226eccd2f63",
          "name": "mooseborzoi",
          "tier": "ELITE",
          "totalPnl": 341627,
          "sportPnlTotal": 341627,
          "outcome": "Los Angeles Dodgers",
          "side": "home",
          "marketType": "ml",
          "size": 13,
          "avgPrice": 0.76,
          "invested": 10,
          "curPrice": 0.725,
          "currentValue": 9,
          "pnl": 0,
          "firstSeen": "2026-04-26T22:02:49.375Z",
          "sportPnl": 341627,
          "sportVerified": true,
          "sportROI": 6.5,
          "avgSportBet": 6945,
          "leaderboardRank": 196,
          "sportsLbPercentileTop": 87,
          "sportVol": 5244292.9169510035,
          "monthlyPnl": 341627.2713669236,
          "monthlyQualified": true
        },
        {
          "wallet": "0x84cfffc3f16dcc353094de30d4a45226eccd2f63",
          "name": "mooseborzoi",
          "tier": "ELITE",
          "totalPnl": 341627,
          "sportPnlTotal": 341627,
          "outcome": "Los Angeles Dodgers",
          "side": "home",
          "marketType": "ml",
          "size": 2,
          "avgPrice": 0.67,
          "invested": 1,
          "curPrice": 0.685,
          "currentValue": 1,
          "pnl": 0,
          "firstSeen": "2026-04-26T22:02:49.375Z",
          "sportPnl": 341627,
          "sportVerified": true,
          "sportROI": 6.5,
          "avgSportBet": 6945,
          "leaderboardRank": 196,
          "sportsLbPercentileTop": 87,
          "sportVol": 5244292.9169510035,
          "monthlyPnl": 341627.2713669236,
          "monthlyQualified": true
        }
      ],
      "summary": {
        "sharpAway": 0,
        "sharpHome": 2,
        "awayInvested": 0,
        "homeInvested": 11,
        "consensus": "home",
        "totalInvested": 11
      }
    },
    "chc_sdp": {
      "away": "Chicago Cubs",
      "home": "San Diego Padres",
      "positions": [
        {
          "wallet": "0x84cfffc3f16dcc353094de30d4a45226eccd2f63",
          "name": "mooseborzoi",
          "tier": "ELITE",
          "totalPnl": 341627,
          "sportPnlTotal": 341627,
          "outcome": "San Diego Padres",
          "side": "home",
          "marketType": "ml",
          "size": 9,
          "avgPrice": 0.51,
          "invested": 5,
          "curPrice": 0.485,
          "currentValue": 4,
          "pnl": 0,
          "firstSeen": "2026-04-27T03:30:01.925Z",
          "sportPnl": 341627,
          "sportVerified": true,
          "sportROI": 6.5,
          "avgSportBet": 6945,
          "leaderboardRank": 196,
          "sportsLbPercentileTop": 87,
          "sportVol": 5244292.9169510035,
          "monthlyPnl": 341627.2713669236,
          "monthlyQualified": true
        },
        {
          "wallet": "0x84cfffc3f16dcc353094de30d4a45226eccd2f63",
          "name": "mooseborzoi",
          "tier": "ELITE",
          "totalPnl": 341627,
          "sportPnlTotal": 341627,
          "outcome": "San Diego Padres",
          "side": "home",
          "marketType": "ml",
          "size": 5,
          "avgPrice": 0.5,
          "invested": 2,
          "curPrice": 0.485,
          "currentValue": 2,
          "pnl": 0,
          "firstSeen": "2026-04-27T03:30:01.925Z",
          "sportPnl": 341627,
          "sportVerified": true,
          "sportROI": 6.5,
          "avgSportBet": 6945,
          "leaderboardRank": 196,
          "sportsLbPercentileTop": 87,
          "sportVol": 5244292.9169510035,
          "monthlyPnl": 341627.2713669236,
          "monthlyQualified": true
        }
      ],
      "summary": {
        "sharpAway": 0,
        "sharpHome": 2,
        "awayInvested": 0,
        "homeInvested": 7,
        "consensus": "home",
        "totalInvested": 7
      }
    },
    "col_cin": {
      "away": "Colorado Rockies",
      "home": "Cincinnati Reds",
      "positions": [
        {
          "wallet": "0x32ccd9015a900fde62040162a04bedf093c668b3",
          "name": "pilotlady",
          "tier": "ELITE",
          "totalPnl": 133140,
          "sportPnlTotal": 133140,
          "outcome": "Colorado Rockies",
          "side": "away",
          "marketType": "ml",
          "size": 6,
          "avgPrice": 0.35,
          "invested": 2,
          "curPrice": 0.345,
          "currentValue": 2,
          "pnl": 0,
          "firstSeen": "2026-04-28T06:45:53.908Z",
          "sportPnl": 133140,
          "sportVerified": true,
          "sportROI": 1,
          "avgSportBet": 1565,
          "leaderboardRank": 434,
          "sportsLbPercentileTop": 71.13,
          "sportVol": 13220632.717709998,
          "monthlyPnl": 133140.4524151096,
          "monthlyQualified": true
        }
      ],
      "summary": {
        "sharpAway": 1,
        "sharpHome": 0,
        "awayInvested": 2,
        "homeInvested": 0,
        "consensus": "away",
        "totalInvested": 2
      }
    }
  },
  "NBA": {
    "atl_nyk": {
      "away": "Hawks",
      "home": "Knicks",
      "positions": [
        {
          "wallet": "0x84cfffc3f16dcc353094de30d4a45226eccd2f63",
          "name": "mooseborzoi",
          "tier": "ELITE",
          "totalPnl": 341627,
          "sportPnlTotal": 341627,
          "outcome": "Hawks",
          "side": "away",
          "marketType": "ml",
          "size": 288833,
          "avgPrice": 0.312,
          "invested": 90145,
          "curPrice": 0.315,
          "currentValue": 90983,
          "pnl": 821,
          "firstSeen": "2026-04-26T03:25:21.164Z",
          "sportPnl": 341627,
          "sportVerified": true,
          "sportROI": 6.5,
          "avgSportBet": 6945,
          "leaderboardRank": 196,
          "sportsLbPercentileTop": 87,
          "sportVol": 5244292.9169510035,
          "monthlyPnl": 341627.2713669236,
          "monthlyQualified": true
        },
        {
          "wallet": "0xbde579ead903b9cf5c3fc4be5a0c515464769c38",
          "name": "thestupidmoney",
          "tier": "ELITE",
          "totalPnl": 948554,
          "sportPnlTotal": 948554,
          "outcome": "Knicks",
          "side": "home",
          "marketType": "ml",
          "size": 55000,
          "avgPrice": 0.684,
          "invested": 37648,
          "curPrice": 0.685,
          "currentValue": 37675,
          "pnl": 25,
          "firstSeen": "2026-04-28T04:07:57.491Z",
          "sportPnl": 948554,
          "sportVerified": true,
          "sportROI": 14.4,
          "avgSportBet": 3508,
          "leaderboardRank": 534,
          "sportsLbPercentileTop": null,
          "sportVol": 6598047
        },
        {
          "wallet": "0x9495425feeb0c250accb89275c97587011b19a27",
          "name": "LaBradfordSmith22",
          "tier": "ELITE",
          "totalPnl": 1972540,
          "sportPnlTotal": 1972540,
          "outcome": "Knicks",
          "side": "home",
          "marketType": "ml",
          "size": 10693,
          "avgPrice": 0.7,
          "invested": 7485,
          "curPrice": 0.685,
          "currentValue": 7325,
          "pnl": -160,
          "firstSeen": "2026-04-28T04:03:05.845Z",
          "sportPnl": 1972540,
          "sportVerified": true,
          "sportROI": 10.6,
          "avgSportBet": 10448,
          "leaderboardRank": 29,
          "sportsLbPercentileTop": 98.13,
          "sportVol": 18581733.987129,
          "monthlyPnl": 1972540.2931408533,
          "monthlyQualified": true
        },
        {
          "wallet": "0xc8ab97a9089a9ff7e6ef0688e6e591a066946418",
          "name": "ArmageddonRewardsBilly",
          "tier": "ELITE",
          "totalPnl": 463223,
          "sportPnlTotal": 463223,
          "outcome": "Knicks",
          "side": "home",
          "marketType": "ml",
          "size": 2000,
          "avgPrice": 0.7,
          "invested": 1400,
          "curPrice": 0.685,
          "currentValue": 1370,
          "pnl": -30,
          "firstSeen": "2026-04-28T04:08:18.017Z",
          "sportPnl": 463223,
          "sportVerified": true,
          "sportROI": 25.5,
          "avgSportBet": 11933,
          "leaderboardRank": null,
          "sportsLbPercentileTop": null,
          "sportVol": 1813760
        },
        {
          "wallet": "0x84cfffc3f16dcc353094de30d4a45226eccd2f63",
          "name": "mooseborzoi",
          "tier": "ELITE",
          "totalPnl": 341627,
          "sportPnlTotal": 341627,
          "outcome": "Hawks",
          "side": "away",
          "marketType": "ml",
          "size": 1585,
          "avgPrice": 0.385,
          "invested": 610,
          "curPrice": 0.31,
          "currentValue": 491,
          "pnl": -119,
          "firstSeen": "2026-04-26T03:25:21.164Z",
          "sportPnl": 341627,
          "sportVerified": true,
          "sportROI": 6.5,
          "avgSportBet": 6945,
          "leaderboardRank": 196,
          "sportsLbPercentileTop": 87,
          "sportVol": 5244292.9169510035,
          "monthlyPnl": 341627.2713669236,
          "monthlyQualified": true
        },
        {
          "wallet": "0x1117eade222413335b7ec959e5b48c1d3dbc3532",
          "name": "benwyatt",
          "tier": "ELITE",
          "totalPnl": 219420,
          "sportPnlTotal": 219420,
          "outcome": "Knicks",
          "side": "home",
          "marketType": "ml",
          "size": 689,
          "avgPrice": 0.47,
          "invested": 324,
          "curPrice": 0.69,
          "currentValue": 475,
          "pnl": 151,
          "firstSeen": "2026-04-28T00:43:34.377Z",
          "sportPnl": 219420,
          "sportVerified": true,
          "sportROI": 3.1,
          "avgSportBet": 9859,
          "leaderboardRank": 102,
          "sportsLbPercentileTop": 89.9,
          "sportVol": 7027404.434521999,
          "monthlyPnl": 219420.06354367128,
          "monthlyQualified": true
        },
        {
          "wallet": "0x53757615de1c42b83f893b79d4241a009dc2aeea",
          "name": "0x53757615de1c42b83f893b79d4241a009dc2aeea",
          "tier": "ELITE",
          "totalPnl": 390937,
          "sportPnlTotal": 390937,
          "outcome": "Hawks",
          "side": "away",
          "marketType": "ml",
          "size": 268,
          "avgPrice": 0.29,
          "invested": 78,
          "curPrice": 0.315,
          "currentValue": 84,
          "pnl": 7,
          "firstSeen": "2026-04-28T01:46:25.517Z",
          "sportPnl": 390937,
          "sportVerified": true,
          "sportROI": 2.3,
          "avgSportBet": 11191,
          "leaderboardRank": 53,
          "sportsLbPercentileTop": 94.8,
          "sportVol": 17289890.6299,
          "monthlyPnl": 390937.3440124751,
          "monthlyQualified": true
        }
      ],
      "summary": {
        "sharpAway": 3,
        "sharpHome": 4,
        "awayInvested": 90833,
        "homeInvested": 46857,
        "consensus": "away",
        "totalInvested": 137690
      }
    },
    "hou_lal": {
      "away": "Rockets",
      "home": "Lakers",
      "positions": [
        {
          "wallet": "0x84dbb7103982e3617704a2ed7d5b39691952aeeb",
          "name": "Soarin22",
          "tier": "ELITE",
          "totalPnl": 1672035,
          "sportPnlTotal": 1672035,
          "outcome": "Lakers",
          "side": "home",
          "marketType": "ml",
          "size": 24587,
          "avgPrice": 0.55,
          "invested": 13523,
          "curPrice": 0.886,
          "currentValue": 21797,
          "pnl": 8274,
          "firstSeen": "2026-04-28T01:45:02.632Z",
          "sportPnl": 1672035,
          "sportVerified": true,
          "sportROI": 2.4,
          "avgSportBet": 10813,
          "leaderboardRank": 33,
          "sportsLbPercentileTop": 97.87,
          "sportVol": 68876402.159958,
          "monthlyPnl": 641943.4686135859,
          "monthlyQualified": true
        },
        {
          "wallet": "0x53757615de1c42b83f893b79d4241a009dc2aeea",
          "name": "0x53757615de1c42b83f893b79d4241a009dc2aeea",
          "tier": "ELITE",
          "totalPnl": 390937,
          "sportPnlTotal": 390937,
          "outcome": "Lakers",
          "side": "home",
          "marketType": "ml",
          "size": 3664,
          "avgPrice": 0.58,
          "invested": 2126,
          "curPrice": 0.585,
          "currentValue": 2144,
          "pnl": 17,
          "firstSeen": "2026-04-28T01:46:25.511Z",
          "sportPnl": 390937,
          "sportVerified": true,
          "sportROI": 2.3,
          "avgSportBet": 11191,
          "leaderboardRank": 53,
          "sportsLbPercentileTop": 94.8,
          "sportVol": 17289890.6299,
          "monthlyPnl": 390937.3440124751,
          "monthlyQualified": true
        },
        {
          "wallet": "0x84cfffc3f16dcc353094de30d4a45226eccd2f63",
          "name": "mooseborzoi",
          "tier": "ELITE",
          "totalPnl": 341627,
          "sportPnlTotal": 341627,
          "outcome": "Rockets",
          "side": "away",
          "marketType": "ml",
          "size": 671,
          "avgPrice": 0.347,
          "invested": 233,
          "curPrice": 0.114,
          "currentValue": 76,
          "pnl": -157,
          "firstSeen": "2026-04-27T06:34:36.129Z",
          "sportPnl": 341627,
          "sportVerified": true,
          "sportROI": 6.5,
          "avgSportBet": 6945,
          "leaderboardRank": 196,
          "sportsLbPercentileTop": 87,
          "sportVol": 5244292.9169510035,
          "monthlyPnl": 341627.2713669236,
          "monthlyQualified": true
        },
        {
          "wallet": "0x1117eade222413335b7ec959e5b48c1d3dbc3532",
          "name": "benwyatt",
          "tier": "ELITE",
          "totalPnl": 219420,
          "sportPnlTotal": 219420,
          "outcome": "Lakers",
          "side": "home",
          "marketType": "ml",
          "size": 1456,
          "avgPrice": 0.16,
          "invested": 233,
          "curPrice": 0.886,
          "currentValue": 1291,
          "pnl": 1058,
          "firstSeen": "2026-04-28T00:43:34.377Z",
          "sportPnl": 219420,
          "sportVerified": true,
          "sportROI": 3.1,
          "avgSportBet": 9859,
          "leaderboardRank": 102,
          "sportsLbPercentileTop": 89.9,
          "sportVol": 7027404.434521999,
          "monthlyPnl": 219420.06354367128,
          "monthlyQualified": true
        },
        {
          "wallet": "0x84cfffc3f16dcc353094de30d4a45226eccd2f63",
          "name": "mooseborzoi",
          "tier": "ELITE",
          "totalPnl": 341627,
          "sportPnlTotal": 341627,
          "outcome": "Rockets",
          "side": "away",
          "marketType": "ml",
          "size": 502,
          "avgPrice": 0.417,
          "invested": 210,
          "curPrice": 0.415,
          "currentValue": 208,
          "pnl": -1,
          "firstSeen": "2026-04-27T06:34:36.129Z",
          "sportPnl": 341627,
          "sportVerified": true,
          "sportROI": 6.5,
          "avgSportBet": 6945,
          "leaderboardRank": 196,
          "sportsLbPercentileTop": 87,
          "sportVol": 5244292.9169510035,
          "monthlyPnl": 341627.2713669236,
          "monthlyQualified": true
        }
      ],
      "summary": {
        "sharpAway": 2,
        "sharpHome": 3,
        "awayInvested": 443,
        "homeInvested": 15882,
        "consensus": "home",
        "totalInvested": 16325
      }
    },
    "orl_det": {
      "away": "Magic",
      "home": "Pistons",
      "positions": [
        {
          "wallet": "0xc8ec6d4cef5c5fe8409ef69303c37f05b678e8f1",
          "name": "Hugewinner",
          "tier": "ELITE",
          "totalPnl": 489303,
          "sportPnlTotal": 489303,
          "outcome": "Magic",
          "side": "away",
          "marketType": "ml",
          "size": 17162,
          "avgPrice": 0.285,
          "invested": 4889,
          "curPrice": 0.69,
          "currentValue": 11840,
          "pnl": 6950,
          "firstSeen": "2026-04-28T04:04:20.324Z",
          "sportPnl": 489303,
          "sportVerified": true,
          "sportROI": 9.8,
          "avgSportBet": 4226,
          "leaderboardRank": 152,
          "sportsLbPercentileTop": 89.93,
          "sportVol": 5013028.036257,
          "monthlyPnl": 274518.26898221707,
          "monthlyQualified": true
        },
        {
          "wallet": "0x84dbb7103982e3617704a2ed7d5b39691952aeeb",
          "name": "Soarin22",
          "tier": "ELITE",
          "totalPnl": 1672035,
          "sportPnlTotal": 1672035,
          "outcome": "Magic",
          "side": "away",
          "marketType": "ml",
          "size": 3867,
          "avgPrice": 0.25,
          "invested": 967,
          "curPrice": 0.69,
          "currentValue": 2668,
          "pnl": 1701,
          "firstSeen": "2026-04-28T04:02:51.464Z",
          "sportPnl": 1672035,
          "sportVerified": true,
          "sportROI": 2.4,
          "avgSportBet": 10813,
          "leaderboardRank": 33,
          "sportsLbPercentileTop": 97.87,
          "sportVol": 68876402.159958,
          "monthlyPnl": 641943.4686135859,
          "monthlyQualified": true
        },
        {
          "wallet": "0x84cfffc3f16dcc353094de30d4a45226eccd2f63",
          "name": "mooseborzoi",
          "tier": "ELITE",
          "totalPnl": 341627,
          "sportPnlTotal": 341627,
          "outcome": "Pistons",
          "side": "home",
          "marketType": "ml",
          "size": 290,
          "avgPrice": 0.701,
          "invested": 203,
          "curPrice": 0.765,
          "currentValue": 222,
          "pnl": 18,
          "firstSeen": "2026-04-28T04:04:44.720Z",
          "sportPnl": 341627,
          "sportVerified": true,
          "sportROI": 6.5,
          "avgSportBet": 6945,
          "leaderboardRank": 196,
          "sportsLbPercentileTop": 87,
          "sportVol": 5244292.9169510035,
          "monthlyPnl": 341627.2713669236,
          "monthlyQualified": true
        },
        {
          "wallet": "0x84cfffc3f16dcc353094de30d4a45226eccd2f63",
          "name": "mooseborzoi",
          "tier": "ELITE",
          "totalPnl": 341627,
          "sportPnlTotal": 341627,
          "outcome": "Magic",
          "side": "away",
          "marketType": "ml",
          "size": 35,
          "avgPrice": 0.24,
          "invested": 8,
          "curPrice": 0.235,
          "currentValue": 8,
          "pnl": 0,
          "firstSeen": "2026-04-28T09:36:51.461Z",
          "sportPnl": 341627,
          "sportVerified": true,
          "sportROI": 6.5,
          "avgSportBet": 6945,
          "leaderboardRank": 196,
          "sportsLbPercentileTop": 87,
          "sportVol": 5244292.9169510035,
          "monthlyPnl": 341627.2713669236,
          "monthlyQualified": true
        }
      ],
      "summary": {
        "sharpAway": 3,
        "sharpHome": 1,
        "awayInvested": 5864,
        "homeInvested": 203,
        "consensus": "away",
        "totalInvested": 6067
      }
    },
    "por_sas": {
      "away": "Trail Blazers",
      "home": "Spurs",
      "positions": [
        {
          "wallet": "0x53757615de1c42b83f893b79d4241a009dc2aeea",
          "name": "0x53757615de1c42b83f893b79d4241a009dc2aeea",
          "tier": "ELITE",
          "totalPnl": 390937,
          "sportPnlTotal": 390937,
          "outcome": "Spurs",
          "side": "home",
          "marketType": "ml",
          "size": 15109,
          "avgPrice": 0.848,
          "invested": 12805,
          "curPrice": 0.835,
          "currentValue": 12616,
          "pnl": -189,
          "firstSeen": "2026-04-28T01:46:25.506Z",
          "sportPnl": 390937,
          "sportVerified": true,
          "sportROI": 2.3,
          "avgSportBet": 11191,
          "leaderboardRank": 53,
          "sportsLbPercentileTop": 94.8,
          "sportVol": 17289890.6299,
          "monthlyPnl": 390937.3440124751,
          "monthlyQualified": true
        },
        {
          "wallet": "0xc8ab97a9089a9ff7e6ef0688e6e591a066946418",
          "name": "ArmageddonRewardsBilly",
          "tier": "ELITE",
          "totalPnl": 463223,
          "sportPnlTotal": 463223,
          "outcome": "Spurs",
          "side": "home",
          "marketType": "ml",
          "size": 2000,
          "avgPrice": 0.83,
          "invested": 1660,
          "curPrice": 0.835,
          "currentValue": 1670,
          "pnl": 10,
          "firstSeen": "2026-04-28T00:45:50.311Z",
          "sportPnl": 463223,
          "sportVerified": true,
          "sportROI": 25.5,
          "avgSportBet": 11933,
          "leaderboardRank": null,
          "sportsLbPercentileTop": null,
          "sportVol": 1813760
        },
        {
          "wallet": "0x84cfffc3f16dcc353094de30d4a45226eccd2f63",
          "name": "mooseborzoi",
          "tier": "ELITE",
          "totalPnl": 341627,
          "sportPnlTotal": 341627,
          "outcome": "Trail Blazers",
          "side": "away",
          "marketType": "ml",
          "size": 110,
          "avgPrice": 0.16,
          "invested": 18,
          "curPrice": 0.165,
          "currentValue": 18,
          "pnl": 1,
          "firstSeen": "2026-04-27T17:18:35.683Z",
          "sportPnl": 341627,
          "sportVerified": true,
          "sportROI": 6.5,
          "avgSportBet": 6945,
          "leaderboardRank": 196,
          "sportsLbPercentileTop": 87,
          "sportVol": 5244292.9169510035,
          "monthlyPnl": 341627.2713669236,
          "monthlyQualified": true
        },
        {
          "wallet": "0x84cfffc3f16dcc353094de30d4a45226eccd2f63",
          "name": "mooseborzoi",
          "tier": "ELITE",
          "totalPnl": 341627,
          "sportPnlTotal": 341627,
          "outcome": "Blazers",
          "side": "away",
          "marketType": "ml",
          "size": 1011,
          "avgPrice": 0.015,
          "invested": 15,
          "curPrice": 0.012,
          "currentValue": 12,
          "pnl": -3,
          "firstSeen": "2026-04-27T17:18:35.683Z",
          "sportPnl": 341627,
          "sportVerified": true,
          "sportROI": 6.5,
          "avgSportBet": 6945,
          "leaderboardRank": 196,
          "sportsLbPercentileTop": 87,
          "sportVol": 5244292.9169510035,
          "monthlyPnl": 341627.2713669236,
          "monthlyQualified": true
        }
      ],
      "summary": {
        "sharpAway": 2,
        "sharpHome": 2,
        "awayInvested": 33,
        "homeInvested": 14465,
        "consensus": "home",
        "totalInvested": 14498
      }
    },
    "tor_cle": {
      "away": "Raptors",
      "home": "Cavaliers",
      "positions": [
        {
          "wallet": "0x84cfffc3f16dcc353094de30d4a45226eccd2f63",
          "name": "mooseborzoi",
          "tier": "ELITE",
          "totalPnl": 341627,
          "sportPnlTotal": 341627,
          "outcome": "Raptors",
          "side": "away",
          "marketType": "ml",
          "size": 14792,
          "avgPrice": 0.238,
          "invested": 3522,
          "curPrice": 0.233,
          "currentValue": 3439,
          "pnl": -84,
          "firstSeen": "2026-04-26T20:07:21.148Z",
          "sportPnl": 341627,
          "sportVerified": true,
          "sportROI": 6.5,
          "avgSportBet": 6945,
          "leaderboardRank": 196,
          "sportsLbPercentileTop": 87,
          "sportVol": 5244292.9169510035,
          "monthlyPnl": 341627.2713669236,
          "monthlyQualified": true
        },
        {
          "wallet": "0x53757615de1c42b83f893b79d4241a009dc2aeea",
          "name": "0x53757615de1c42b83f893b79d4241a009dc2aeea",
          "tier": "ELITE",
          "totalPnl": 390937,
          "sportPnlTotal": 390937,
          "outcome": "Cavaliers",
          "side": "home",
          "marketType": "ml",
          "size": 1607,
          "avgPrice": 0.76,
          "invested": 1222,
          "curPrice": 0.755,
          "currentValue": 1214,
          "pnl": -8,
          "firstSeen": "2026-04-28T01:46:25.512Z",
          "sportPnl": 390937,
          "sportVerified": true,
          "sportROI": 2.3,
          "avgSportBet": 11191,
          "leaderboardRank": 53,
          "sportsLbPercentileTop": 94.8,
          "sportVol": 17289890.6299,
          "monthlyPnl": 390937.3440124751,
          "monthlyQualified": true
        },
        {
          "wallet": "0x84cfffc3f16dcc353094de30d4a45226eccd2f63",
          "name": "mooseborzoi",
          "tier": "ELITE",
          "totalPnl": 341627,
          "sportPnlTotal": 341627,
          "outcome": "Raptors",
          "side": "away",
          "marketType": "ml",
          "size": 6,
          "avgPrice": 0.267,
          "invested": 2,
          "curPrice": 0.245,
          "currentValue": 2,
          "pnl": 0,
          "firstSeen": "2026-04-26T20:07:21.148Z",
          "sportPnl": 341627,
          "sportVerified": true,
          "sportROI": 6.5,
          "avgSportBet": 6945,
          "leaderboardRank": 196,
          "sportsLbPercentileTop": 87,
          "sportVol": 5244292.9169510035,
          "monthlyPnl": 341627.2713669236,
          "monthlyQualified": true
        }
      ],
      "summary": {
        "sharpAway": 2,
        "sharpHome": 1,
        "awayInvested": 3524,
        "homeInvested": 1222,
        "consensus": "away",
        "totalInvested": 4746
      }
    },
    "phi_bos": {
      "away": "76ers",
      "home": "Celtics",
      "positions": [
        {
          "wallet": "0xc8ab97a9089a9ff7e6ef0688e6e591a066946418",
          "name": "ArmageddonRewardsBilly",
          "tier": "ELITE",
          "totalPnl": 463223,
          "sportPnlTotal": 463223,
          "outcome": "Celtics",
          "side": "home",
          "marketType": "ml",
          "size": 2000,
          "avgPrice": 0.82,
          "invested": 1640,
          "curPrice": 0.825,
          "currentValue": 1650,
          "pnl": 10,
          "firstSeen": "2026-04-28T04:28:04.109Z",
          "sportPnl": 463223,
          "sportVerified": true,
          "sportROI": 25.5,
          "avgSportBet": 11933,
          "leaderboardRank": null,
          "sportsLbPercentileTop": null,
          "sportVol": 1813760
        },
        {
          "wallet": "0x84cfffc3f16dcc353094de30d4a45226eccd2f63",
          "name": "mooseborzoi",
          "tier": "ELITE",
          "totalPnl": 341627,
          "sportPnlTotal": 341627,
          "outcome": "Celtics",
          "side": "home",
          "marketType": "ml",
          "size": 855,
          "avgPrice": 0.848,
          "invested": 725,
          "curPrice": 0.973,
          "currentValue": 832,
          "pnl": 106,
          "firstSeen": "2026-04-27T03:30:01.925Z",
          "sportPnl": 341627,
          "sportVerified": true,
          "sportROI": 6.5,
          "avgSportBet": 6945,
          "leaderboardRank": 196,
          "sportsLbPercentileTop": 87,
          "sportVol": 5244292.9169510035,
          "monthlyPnl": 341627.2713669236,
          "monthlyQualified": true
        },
        {
          "wallet": "0x53757615de1c42b83f893b79d4241a009dc2aeea",
          "name": "0x53757615de1c42b83f893b79d4241a009dc2aeea",
          "tier": "ELITE",
          "totalPnl": 390937,
          "sportPnlTotal": 390937,
          "outcome": "Celtics",
          "side": "home",
          "marketType": "ml",
          "size": 641,
          "avgPrice": 0.826,
          "invested": 529,
          "curPrice": 0.825,
          "currentValue": 529,
          "pnl": 0,
          "firstSeen": "2026-04-28T01:46:25.515Z",
          "sportPnl": 390937,
          "sportVerified": true,
          "sportROI": 2.3,
          "avgSportBet": 11191,
          "leaderboardRank": 53,
          "sportsLbPercentileTop": 94.8,
          "sportVol": 17289890.6299,
          "monthlyPnl": 390937.3440124751,
          "monthlyQualified": true
        },
        {
          "wallet": "0x84cfffc3f16dcc353094de30d4a45226eccd2f63",
          "name": "mooseborzoi",
          "tier": "ELITE",
          "totalPnl": 341627,
          "sportPnlTotal": 341627,
          "outcome": "76ers",
          "side": "away",
          "marketType": "ml",
          "size": 2069,
          "avgPrice": 0.18,
          "invested": 372,
          "curPrice": 0.175,
          "currentValue": 362,
          "pnl": -10,
          "firstSeen": "2026-04-27T17:10:37.833Z",
          "sportPnl": 341627,
          "sportVerified": true,
          "sportROI": 6.5,
          "avgSportBet": 6945,
          "leaderboardRank": 196,
          "sportsLbPercentileTop": 87,
          "sportVol": 5244292.9169510035,
          "monthlyPnl": 341627.2713669236,
          "monthlyQualified": true
        }
      ],
      "summary": {
        "sharpAway": 1,
        "sharpHome": 3,
        "awayInvested": 372,
        "homeInvested": 2894,
        "consensus": "home",
        "totalInvested": 3266
      }
    },
    "den_min": {
      "away": "Nuggets",
      "home": "Timberwolves",
      "positions": [
        {
          "wallet": "0x339a0e5aea39a7db5cea5b0003abab33c78c1eae",
          "name": "Tokidoki",
          "tier": "ELITE",
          "totalPnl": 246882,
          "sportPnlTotal": 246882,
          "outcome": "Nuggets",
          "side": "away",
          "marketType": "ml",
          "size": 6318,
          "avgPrice": 0.395,
          "invested": 2494,
          "curPrice": 0.57,
          "currentValue": 3601,
          "pnl": 1107,
          "firstSeen": "2026-04-28T06:43:50.525Z",
          "sportPnl": 246882,
          "sportVerified": true,
          "sportROI": 5,
          "avgSportBet": 1285,
          "leaderboardRank": 253,
          "sportsLbPercentileTop": 83.2,
          "sportVol": 4966119.728227001,
          "monthlyPnl": 145589.73986904556,
          "monthlyQualified": true
        },
        {
          "wallet": "0x84cfffc3f16dcc353094de30d4a45226eccd2f63",
          "name": "mooseborzoi",
          "tier": "ELITE",
          "totalPnl": 341627,
          "sportPnlTotal": 341627,
          "outcome": "Nuggets",
          "side": "away",
          "marketType": "ml",
          "size": 1879,
          "avgPrice": 0.517,
          "invested": 971,
          "curPrice": 0.57,
          "currentValue": 1071,
          "pnl": 100,
          "firstSeen": "2026-04-28T06:43:15.808Z",
          "sportPnl": 341627,
          "sportVerified": true,
          "sportROI": 6.5,
          "avgSportBet": 6945,
          "leaderboardRank": 196,
          "sportsLbPercentileTop": 87,
          "sportVol": 5244292.9169510035,
          "monthlyPnl": 341627.2713669236,
          "monthlyQualified": true
        }
      ],
      "summary": {
        "sharpAway": 2,
        "sharpHome": 0,
        "awayInvested": 3465,
        "homeInvested": 0,
        "consensus": "away",
        "totalInvested": 3465
      }
    }
  },
  "scannedAt": "2026-04-28T09:55:45.049Z",
  "walletsScanned": 296,
  "mmExcluded": 386,
  "sportLosersExcluded": 0,
  "noSportExcluded": 0,
  "tradersExcluded": 5,
  "totalExcluded": 391
}